MANIFEST.in
clibscamperctrl.pxd
cscamper_addr.pxd
cscamper_dealias.pxd
cscamper_file.pxd
cscamper_host.pxd
cscamper_http.pxd
cscamper_icmpext.pxd
cscamper_list.pxd
cscamper_neighbourdisc.pxd
cscamper_owamp.pxd
cscamper_ping.pxd
cscamper_sniff.pxd
cscamper_sting.pxd
cscamper_tbit.pxd
cscamper_trace.pxd
cscamper_tracelb.pxd
cscamper_udpprobe.pxd
scamper.c
scamper.pyi
scamper.pyx
setup.py
scamper.egg-info/PKG-INFO
scamper.egg-info/SOURCES.txt
scamper.egg-info/dependency_links.txt
scamper.egg-info/top_level.txt