Metadata-Version: 2.1
Name: scamper
Version: 20260105
Summary: A module to interact with scamper processes and data
Home-page: https://www.caida.org/tools/measurement/scamper/
Author: Matthew Luckie
Author-email: mjl@luckie.org.nz
License: GPL-2.0-only
Project-URL: Documentation, https://www.caida.org/catalog/software/scamper/python/
Keywords: Internet measurement,ping,traceroute,dns,http,alias resolution
Classifier: Programming Language :: Python :: 3
Classifier: Intended Audience :: Developers
Classifier: Intended Audience :: Science/Research
Classifier: License :: OSI Approved :: GNU General Public License v2 (GPLv2)
Classifier: Operating System :: OS Independent
Classifier: Topic :: Internet
Classifier: Topic :: Software Development :: Libraries :: Python Modules
Classifier: Topic :: Scientific/Engineering
